src/pytest_kexi/__init__.py
src/pytest_kexi/helper.py
src/pytest_kexi/plugin.py
pytest_kexi-0.10.1.dist-info/entry_points.txt
pytest_kexi-0.10.1.dist-info/WHEEL
pytest_kexi-0.10.1.dist-info/METADATA
pytest_kexi-0.10.1.dist-info/RECORD
